TOPSIS_package/cli.py
topsis_neeraj-0.0.1.dist-info/LICENSE.txt
topsis_neeraj-0.0.1.dist-info/METADATA
topsis_neeraj-0.0.1.dist-info/WHEEL
topsis_neeraj-0.0.1.dist-info/entry_points.txt
topsis_neeraj-0.0.1.dist-info/top_level.txt
topsis_neeraj-0.0.1.dist-info/RECORD
