Metadata-Version: 2.1
Name: topsis-neeraj
Version: 0.0.1
Summary: Topsis Analysis
Home-page: https://pypi.org/project/topsis-neeraj
Author: Neeraj Kapoor
Author-email: nkapoor50_be18@thapar.edu
License: MIT
Platform: UNKNOWN
Classifier: License :: OSI Approved :: MIT License
Classifier: Programming Language :: Python :: 3
Classifier: Programming Language :: Python :: 3.7
Requires-Dist: numpy
Requires-Dist: pandas
